{"type":"Image","props":{"y":0,"x":0,"width":720,"var":"sprBg","skin":"comp/img_bg3.png","presetID":1,"name":"InitUI","isPresetRoot":true,"height":1280,"sizeGrid":"11,24,11,20","text":"加载初始资源......","fontSize":50,"color":"#010000","anchorY":0,"anchorX":0},"compId":24,"child":[{"type":"Script","props":{"y":0,"x":0,"presetID":2,"runtime":"script/scene/initScene/InitUI.ts"},"compId":29},{"type":"Sprite","props":{"y":615,"x":168.3251953125,"presetID":4,"name":"nodCenter"},"compId":36,"child":[{"type":"Label","props":{"y":0,"x":0,"text":"加载初始资源......","presetID":3,"fontSize":50,"color":"#010000","anchorY":0,"anchorX":0},"compId":35}]}],"loadList":["comp/img_bg3.png"],"loadList3D":[]}